odoo/addons/sale_margin_delivered_security/README.rst
odoo/addons/sale_margin_delivered_security/__init__.py
odoo/addons/sale_margin_delivered_security/__manifest__.py
odoo/addons/sale_margin_delivered_security/i18n/it.po
odoo/addons/sale_margin_delivered_security/i18n/sale_margin_delivered_security.pot
odoo/addons/sale_margin_delivered_security/models/__init__.py
odoo/addons/sale_margin_delivered_security/models/sale_order_line.py
odoo/addons/sale_margin_delivered_security/readme/CONTRIBUTORS.rst
odoo/addons/sale_margin_delivered_security/readme/DESCRIPTION.rst
odoo/addons/sale_margin_delivered_security/static/description/icon.png
odoo/addons/sale_margin_delivered_security/static/description/index.html
odoo_addon_sale_margin_delivered_security-16.0.1.2.1.6.dist-info/METADATA
odoo_addon_sale_margin_delivered_security-16.0.1.2.1.6.dist-info/WHEEL
odoo_addon_sale_margin_delivered_security-16.0.1.2.1.6.dist-info/top_level.txt
odoo_addon_sale_margin_delivered_security-16.0.1.2.1.6.dist-info/RECORD
