Metadata-Version: 2.1
Name: odoo-addon-sale-margin-delivered-security
Version: 16.0.1.2.1.6
Summary: Glue module between sale margin delivered and sale margin security modules
Home-page: https://github.com/OCA/margin-analysis
Author: Tecnativa, GRAP, Odoo Community Association (OCA)
Author-email: support@odoo-community.org
License: AGPL-3
Platform: UNKNOWN
Classifier: Programming Language :: Python
Classifier: Framework :: Odoo
Classifier: Framework :: Odoo :: 16.0
Classifier: License :: OSI Approved :: GNU Affero General Public License v3
Requires-Python: >=3.10
Requires-Dist: odoo-addon-sale-margin-delivered <16.1dev,>=16.0dev
Requires-Dist: odoo-addon-sale-margin-security <16.1dev,>=16.0dev
Requires-Dist: odoo <16.1dev,>=16.0a
